<annotation>
  <folder>/home/nng/util/CocoToPascal/images</folder>
  <filename>000000513145.jpg</filename>
  <source>
    <database>MS COCO 2017</database>
    <annotation>MS COCO 2017</annotation>
    <image>Flickr</image>
  </source>
  <size>
    <width>640</width>
    <height>427</height>
    <depth>3</depth>
  </size>
  <segmented>0</segmented>
  <object>
    <name>umbrella</name>
    <bndbox>
      <xmin>241.81</xmin>
      <ymin>36.46</ymin>
      <xmax>582.45</xmax>
      <ymax>284.03</ymax>
    </bndbox>
  </object>
  <object>
    <name>backpack</name>
    <bndbox>
      <xmin>426.46</xmin>
      <ymin>249.51</ymin>
      <xmax>634.66</xmax>
      <ymax>427.0</ymax>
    </bndbox>
  </object>
  <object>
    <name>backpack</name>
    <bndbox>
      <xmin>1.91</xmin>
      <ymin>186.69</ymin>
      <xmax>225.95</xmax>
      <ymax>422.21000000000004</ymax>
    </bndbox>
  </object>
  <object>
    <name>person</name>
    <bndbox>
      <xmin>386.7</xmin>
      <ymin>132.42</ymin>
      <xmax>640.0</xmax>
      <ymax>427.0</ymax>
    </bndbox>
  </object>
  <object>
    <name>person</name>
    <bndbox>
      <xmin>233.08</xmin>
      <ymin>114.31</ymin>
      <xmax>432.73</xmax>
      <ymax>419.04</ymax>
    </bndbox>
  </object>
  <object>
    <name>person</name>
    <bndbox>
      <xmin>107.47</xmin>
      <ymin>59.49</ymin>
      <xmax>297.46000000000004</xmax>
      <ymax>420.28000000000003</ymax>
    </bndbox>
  </object>
  <object>
    <name>person</name>
    <bndbox>
      <xmin>592.53</xmin>
      <ymin>215.08</ymin>
      <xmax>630.48</xmax>
      <ymax>268.85</ymax>
    </bndbox>
  </object>
</annotation>
