<annotation>
  <folder>/home/nng/util/CocoToPascal/images</folder>
  <filename>000000032578.jpg</filename>
  <source>
    <database>MS COCO 2017</database>
    <annotation>MS COCO 2017</annotation>
    <image>Flickr</image>
  </source>
  <size>
    <width>375</width>
    <height>500</height>
    <depth>3</depth>
  </size>
  <segmented>0</segmented>
  <object>
    <name>animal</name>
    <bndbox>
      <xmin>153.02</xmin>
      <ymin>193.43</ymin>
      <xmax>293.1</xmax>
      <ymax>353.99</ymax>
    </bndbox>
  </object>
  <object>
    <name>person</name>
    <bndbox>
      <xmin>3.37</xmin>
      <ymin>4.49</ymin>
      <xmax>216.85</xmax>
      <ymax>492.13</ymax>
    </bndbox>
  </object>
  <object>
    <name>oven</name>
    <bndbox>
      <xmin>2.25</xmin>
      <ymin>117.64</ymin>
      <xmax>201.12</xmax>
      <ymax>326.63</ymax>
    </bndbox>
  </object>
  <object>
    <name>pizza</name>
    <bndbox>
      <xmin>67.14</xmin>
      <ymin>365.6</ymin>
      <xmax>368.5</xmax>
      <ymax>500.0</ymax>
    </bndbox>
  </object>
</annotation>
