<annotation>
  <folder>/home/nng/util/CocoToPascal/images</folder>
  <filename>000000568462.jpg</filename>
  <source>
    <database>MS COCO 2017</database>
    <annotation>MS COCO 2017</annotation>
    <image>Flickr</image>
  </source>
  <size>
    <width>428</width>
    <height>640</height>
    <depth>3</depth>
  </size>
  <segmented>0</segmented>
  <object>
    <name>sports ball</name>
    <bndbox>
      <xmin>360.35</xmin>
      <ymin>245.85</ymin>
      <xmax>374.67</xmax>
      <ymax>259.7</ymax>
    </bndbox>
  </object>
  <object>
    <name>person</name>
    <bndbox>
      <xmin>60.4</xmin>
      <ymin>135.19</ymin>
      <xmax>398.38</xmax>
      <ymax>578.1600000000001</ymax>
    </bndbox>
  </object>
  <object>
    <name>baseball glove</name>
    <bndbox>
      <xmin>57.37</xmin>
      <ymin>185.95</ymin>
      <xmax>101.77</xmax>
      <ymax>253.01</ymax>
    </bndbox>
  </object>
</annotation>
