<annotation>
  <folder>/home/nng/util/CocoToPascal/images</folder>
  <filename>000000151172.jpg</filename>
  <source>
    <database>MS COCO 2017</database>
    <annotation>MS COCO 2017</annotation>
    <image>Flickr</image>
  </source>
  <size>
    <width>640</width>
    <height>384</height>
    <depth>3</depth>
  </size>
  <segmented>0</segmented>
  <object>
    <name>person</name>
    <bndbox>
      <xmin>257.63</xmin>
      <ymin>27.35</ymin>
      <xmax>403.75</xmax>
      <ymax>189.67</ymax>
    </bndbox>
  </object>
  <object>
    <name>person</name>
    <bndbox>
      <xmin>144.75</xmin>
      <ymin>301.38</ymin>
      <xmax>169.66</xmax>
      <ymax>353.49</ymax>
    </bndbox>
  </object>
  <object>
    <name>person</name>
    <bndbox>
      <xmin>450.32</xmin>
      <ymin>295.25</ymin>
      <xmax>492.25</xmax>
      <ymax>322.79</ymax>
    </bndbox>
  </object>
  <object>
    <name>person</name>
    <bndbox>
      <xmin>603.15</xmin>
      <ymin>94.96</ymin>
      <xmax>617.3199999999999</xmax>
      <ymax>134.01</ymax>
    </bndbox>
  </object>
  <object>
    <name>person</name>
    <bndbox>
      <xmin>521.32</xmin>
      <ymin>103.03</ymin>
      <xmax>534.47</xmax>
      <ymax>119.38</ymax>
    </bndbox>
  </object>
  <object>
    <name>person</name>
    <bndbox>
      <xmin>92.67</xmin>
      <ymin>317.02</ymin>
      <xmax>126.55000000000001</xmax>
      <ymax>367.46999999999997</ymax>
    </bndbox>
  </object>
  <object>
    <name>bench</name>
    <bndbox>
      <xmin>519.41</xmin>
      <ymin>117.97</ymin>
      <xmax>540.26</xmax>
      <ymax>128.62</ymax>
    </bndbox>
  </object>
  <object>
    <name>bench</name>
    <bndbox>
      <xmin>533.92</xmin>
      <ymin>114.71</ymin>
      <xmax>543.8299999999999</xmax>
      <ymax>118.78</ymax>
    </bndbox>
  </object>
  <object>
    <name>bench</name>
    <bndbox>
      <xmin>129.84</xmin>
      <ymin>344.12</ymin>
      <xmax>178.8</xmax>
      <ymax>377.71000000000004</ymax>
    </bndbox>
  </object>
  <object>
    <name>bench</name>
    <bndbox>
      <xmin>511.43</xmin>
      <ymin>143.74</ymin>
      <xmax>555.87</xmax>
      <ymax>167.67000000000002</ymax>
    </bndbox>
  </object>
  <object>
    <name>person</name>
    <bndbox>
      <xmin>545.67</xmin>
      <ymin>102.44</ymin>
      <xmax>557.8399999999999</xmax>
      <ymax>125.85</ymax>
    </bndbox>
  </object>
  <object>
    <name>person</name>
    <bndbox>
      <xmin>60.67</xmin>
      <ymin>305.81</ymin>
      <xmax>66.29</xmax>
      <ymax>338.37</ymax>
    </bndbox>
  </object>
  <object>
    <name>person</name>
    <bndbox>
      <xmin>257.43</xmin>
      <ymin>342.67</ymin>
      <xmax>292.86</xmax>
      <ymax>380.35</ymax>
    </bndbox>
  </object>
  <object>
    <name>chair</name>
    <bndbox>
      <xmin>112.24</xmin>
      <ymin>341.01</ymin>
      <xmax>126.47999999999999</xmax>
      <ymax>364.71999999999997</ymax>
    </bndbox>
  </object>
  <object>
    <name>potted plant</name>
    <bndbox>
      <xmin>29.73</xmin>
      <ymin>302.33</ymin>
      <xmax>57.74</xmax>
      <ymax>332.59999999999997</ymax>
    </bndbox>
  </object>
  <object>
    <name>oven</name>
    <bndbox>
      <xmin>345.4</xmin>
      <ymin>75.67</ymin>
      <xmax>403.9</xmax>
      <ymax>129.16</ymax>
    </bndbox>
  </object>
  <object>
    <name>oven</name>
    <bndbox>
      <xmin>289.25</xmin>
      <ymin>231.4</ymin>
      <xmax>408.94</xmax>
      <ymax>336.12</ymax>
    </bndbox>
  </object>
  <object>
    <name>oven</name>
    <bndbox>
      <xmin>77.18</xmin>
      <ymin>46.79</ymin>
      <xmax>213.25</xmax>
      <ymax>163.88</ymax>
    </bndbox>
  </object>
  <object>
    <name>oven</name>
    <bndbox>
      <xmin>158.67</xmin>
      <ymin>291.99</ymin>
      <xmax>195.85999999999999</xmax>
      <ymax>329.72</ymax>
    </bndbox>
  </object>
  <object>
    <name>oven</name>
    <bndbox>
      <xmin>485.62</xmin>
      <ymin>194.21</ymin>
      <xmax>637.36</xmax>
      <ymax>372.11</ymax>
    </bndbox>
  </object>
</annotation>
