<annotation>
  <folder>/home/nng/util/CocoToPascal/images</folder>
  <filename>000000540762.jpg</filename>
  <source>
    <database>MS COCO 2017</database>
    <annotation>MS COCO 2017</annotation>
    <image>Flickr</image>
  </source>
  <size>
    <width>640</width>
    <height>514</height>
    <depth>3</depth>
  </size>
  <segmented>0</segmented>
  <object>
    <name>animal</name>
    <bndbox>
      <xmin>264.51</xmin>
      <ymin>176.72</ymin>
      <xmax>629.51</xmax>
      <ymax>477.03999999999996</ymax>
    </bndbox>
  </object>
  <object>
    <name>animal</name>
    <bndbox>
      <xmin>344.05</xmin>
      <ymin>208.06</ymin>
      <xmax>640.0</xmax>
      <ymax>497.6</ymax>
    </bndbox>
  </object>
  <object>
    <name>person</name>
    <bndbox>
      <xmin>102.44</xmin>
      <ymin>74.96</ymin>
      <xmax>137.68</xmax>
      <ymax>127.38</ymax>
    </bndbox>
  </object>
  <object>
    <name>person</name>
    <bndbox>
      <xmin>632.1</xmin>
      <ymin>413.81</ymin>
      <xmax>640.0</xmax>
      <ymax>436.29</ymax>
    </bndbox>
  </object>
  <object>
    <name>person</name>
    <bndbox>
      <xmin>491.64</xmin>
      <ymin>402.83</ymin>
      <xmax>581.38</xmax>
      <ymax>496.84</ymax>
    </bndbox>
  </object>
  <object>
    <name>person</name>
    <bndbox>
      <xmin>566.2</xmin>
      <ymin>423.29</ymin>
      <xmax>593.5600000000001</xmax>
      <ymax>443.42</ymax>
    </bndbox>
  </object>
</annotation>
