<annotation>
  <folder>/home/nng/util/CocoToPascal/images</folder>
  <filename>000000230701.jpg</filename>
  <source>
    <database>MS COCO 2017</database>
    <annotation>MS COCO 2017</annotation>
    <image>Flickr</image>
  </source>
  <size>
    <width>500</width>
    <height>375</height>
    <depth>3</depth>
  </size>
  <segmented>0</segmented>
  <object>
    <name>bottle</name>
    <bndbox>
      <xmin>389.91</xmin>
      <ymin>171.39</ymin>
      <xmax>447.15000000000003</xmax>
      <ymax>365.09</ymax>
    </bndbox>
  </object>
  <object>
    <name>bottle</name>
    <bndbox>
      <xmin>8.03</xmin>
      <ymin>181.56</ymin>
      <xmax>88.33</xmax>
      <ymax>371.06</ymax>
    </bndbox>
  </object>
  <object>
    <name>cell phone</name>
    <bndbox>
      <xmin>215.16</xmin>
      <ymin>40.04</ymin>
      <xmax>254.85</xmax>
      <ymax>117.13999999999999</ymax>
    </bndbox>
  </object>
  <object>
    <name>person</name>
    <bndbox>
      <xmin>2.53</xmin>
      <ymin>4.21</ymin>
      <xmax>249.44</xmax>
      <ymax>357.29999999999995</ymax>
    </bndbox>
  </object>
  <object>
    <name>bottle</name>
    <bndbox>
      <xmin>484.9</xmin>
      <ymin>273.44</ymin>
      <xmax>499.85999999999996</xmax>
      <ymax>374.89</ymax>
    </bndbox>
  </object>
  <object>
    <name>dining table</name>
    <bndbox>
      <xmin>322.2</xmin>
      <ymin>323.07</ymin>
      <xmax>488.02</xmax>
      <ymax>375.0</ymax>
    </bndbox>
  </object>
  <object>
    <name>clock</name>
    <bndbox>
      <xmin>132.38</xmin>
      <ymin>198.11</ymin>
      <xmax>155.13</xmax>
      <ymax>220.49</ymax>
    </bndbox>
  </object>
  <object>
    <name>person</name>
    <bndbox>
      <xmin>174.44</xmin>
      <ymin>58.99</ymin>
      <xmax>394.38</xmax>
      <ymax>365.73</ymax>
    </bndbox>
  </object>
  <object>
    <name>dining table</name>
    <bndbox>
      <xmin>82.35</xmin>
      <ymin>356.88</ymin>
      <xmax>338.28</xmax>
      <ymax>375.0</ymax>
    </bndbox>
  </object>
</annotation>
