<annotation>
  <folder>/home/nng/util/CocoToPascal/images</folder>
  <filename>000000512320.jpg</filename>
  <source>
    <database>MS COCO 2017</database>
    <annotation>MS COCO 2017</annotation>
    <image>Flickr</image>
  </source>
  <size>
    <width>480</width>
    <height>640</height>
    <depth>3</depth>
  </size>
  <segmented>0</segmented>
  <object>
    <name>person</name>
    <bndbox>
      <xmin>100.22</xmin>
      <ymin>76.02</ymin>
      <xmax>432.39</xmax>
      <ymax>575.71</ymax>
    </bndbox>
  </object>
  <object>
    <name>skis</name>
    <bndbox>
      <xmin>1.36</xmin>
      <ymin>345.8</ymin>
      <xmax>309.23</xmax>
      <ymax>635.1800000000001</ymax>
    </bndbox>
  </object>
  <object>
    <name>snowboard</name>
    <bndbox>
      <xmin>105.27</xmin>
      <ymin>49.44</ymin>
      <xmax>257.49</xmax>
      <ymax>273.51</ymax>
    </bndbox>
  </object>
  <object>
    <name>backpack</name>
    <bndbox>
      <xmin>263.19</xmin>
      <ymin>162.52</ymin>
      <xmax>408.45</xmax>
      <ymax>307.78</ymax>
    </bndbox>
  </object>
</annotation>
