<annotation>
  <folder>/home/nng/util/CocoToPascal/images</folder>
  <filename>000000317640.jpg</filename>
  <source>
    <database>MS COCO 2017</database>
    <annotation>MS COCO 2017</annotation>
    <image>Flickr</image>
  </source>
  <size>
    <width>640</width>
    <height>594</height>
    <depth>3</depth>
  </size>
  <segmented>0</segmented>
  <object>
    <name>cake</name>
    <bndbox>
      <xmin>77.07</xmin>
      <ymin>188.83</ymin>
      <xmax>567.4200000000001</xmax>
      <ymax>544.96</ymax>
    </bndbox>
  </object>
</annotation>
