<annotation>
  <folder>/home/nng/util/CocoToPascal/images</folder>
  <filename>000000240646.jpg</filename>
  <source>
    <database>MS COCO 2017</database>
    <annotation>MS COCO 2017</annotation>
    <image>Flickr</image>
  </source>
  <size>
    <width>428</width>
    <height>640</height>
    <depth>3</depth>
  </size>
  <segmented>0</segmented>
  <object>
    <name>potted plant</name>
    <bndbox>
      <xmin>0.0</xmin>
      <ymin>45.96</ymin>
      <xmax>428.0</xmax>
      <ymax>600.5300000000001</ymax>
    </bndbox>
  </object>
  <object>
    <name>vase</name>
    <bndbox>
      <xmin>152.45</xmin>
      <ymin>297.71</ymin>
      <xmax>261.75</xmax>
      <ymax>602.6099999999999</ymax>
    </bndbox>
  </object>
</annotation>
