<annotation>
  <folder>/home/nng/util/CocoToPascal/images</folder>
  <filename>000000162902.jpg</filename>
  <source>
    <database>MS COCO 2017</database>
    <annotation>MS COCO 2017</annotation>
    <image>Flickr</image>
  </source>
  <size>
    <width>500</width>
    <height>332</height>
    <depth>3</depth>
  </size>
  <segmented>0</segmented>
  <object>
    <name>snowboard</name>
    <bndbox>
      <xmin>260.22</xmin>
      <ymin>134.97</ymin>
      <xmax>309.57000000000005</xmax>
      <ymax>315.18</ymax>
    </bndbox>
  </object>
  <object>
    <name>snowboard</name>
    <bndbox>
      <xmin>176.82</xmin>
      <ymin>115.64</ymin>
      <xmax>223.07</xmax>
      <ymax>309.62</ymax>
    </bndbox>
  </object>
  <object>
    <name>snowboard</name>
    <bndbox>
      <xmin>101.01</xmin>
      <ymin>120.46</ymin>
      <xmax>127.01</xmax>
      <ymax>298.71999999999997</ymax>
    </bndbox>
  </object>
  <object>
    <name>snowboard</name>
    <bndbox>
      <xmin>323.79</xmin>
      <ymin>183.53</ymin>
      <xmax>367.07000000000005</xmax>
      <ymax>316.33000000000004</ymax>
    </bndbox>
  </object>
  <object>
    <name>person</name>
    <bndbox>
      <xmin>194.83</xmin>
      <ymin>75.22</ymin>
      <xmax>256.88</xmax>
      <ymax>309.51</ymax>
    </bndbox>
  </object>
  <object>
    <name>person</name>
    <bndbox>
      <xmin>249.4</xmin>
      <ymin>108.86</ymin>
      <xmax>325.71000000000004</xmax>
      <ymax>309.37</ymax>
    </bndbox>
  </object>
  <object>
    <name>person</name>
    <bndbox>
      <xmin>317.25</xmin>
      <ymin>101.7</ymin>
      <xmax>386.36</xmax>
      <ymax>319.11</ymax>
    </bndbox>
  </object>
  <object>
    <name>person</name>
    <bndbox>
      <xmin>94.75</xmin>
      <ymin>101.47</ymin>
      <xmax>182.04000000000002</xmax>
      <ymax>300.66999999999996</ymax>
    </bndbox>
  </object>
  <object>
    <name>person</name>
    <bndbox>
      <xmin>383.39</xmin>
      <ymin>122.34</ymin>
      <xmax>414.0</xmax>
      <ymax>219.76</ymax>
    </bndbox>
  </object>
  <object>
    <name>person</name>
    <bndbox>
      <xmin>401.91</xmin>
      <ymin>129.6</ymin>
      <xmax>414.05</xmax>
      <ymax>148.79999999999998</ymax>
    </bndbox>
  </object>
  <object>
    <name>person</name>
    <bndbox>
      <xmin>467.87</xmin>
      <ymin>149.56</ymin>
      <xmax>482.81</xmax>
      <ymax>202.16</ymax>
    </bndbox>
  </object>
  <object>
    <name>person</name>
    <bndbox>
      <xmin>489.2</xmin>
      <ymin>152.89</ymin>
      <xmax>500.0</xmax>
      <ymax>197.85999999999999</ymax>
    </bndbox>
  </object>
  <object>
    <name>backpack</name>
    <bndbox>
      <xmin>465.25</xmin>
      <ymin>155.15</ymin>
      <xmax>476.62</xmax>
      <ymax>173.02</ymax>
    </bndbox>
  </object>
  <object>
    <name>backpack</name>
    <bndbox>
      <xmin>489.0</xmin>
      <ymin>156.21</ymin>
      <xmax>498.53</xmax>
      <ymax>170.79000000000002</ymax>
    </bndbox>
  </object>
  <object>
    <name>snowboard</name>
    <bndbox>
      <xmin>383.62</xmin>
      <ymin>140.93</ymin>
      <xmax>423.46000000000004</xmax>
      <ymax>198.89000000000001</ymax>
    </bndbox>
  </object>
  <object>
    <name>skis</name>
    <bndbox>
      <xmin>455.82</xmin>
      <ymin>238.32</ymin>
      <xmax>500.0</xmax>
      <ymax>247.01999999999998</ymax>
    </bndbox>
  </object>
</annotation>
