<annotation>
  <folder>/home/nng/util/CocoToPascal/images</folder>
  <filename>000000523487.jpg</filename>
  <source>
    <database>MS COCO 2017</database>
    <annotation>MS COCO 2017</annotation>
    <image>Flickr</image>
  </source>
  <size>
    <width>623</width>
    <height>640</height>
    <depth>3</depth>
  </size>
  <segmented>0</segmented>
  <object>
    <name>bicycle</name>
    <bndbox>
      <xmin>405.65</xmin>
      <ymin>311.22</ymin>
      <xmax>542.7</xmax>
      <ymax>570.24</ymax>
    </bndbox>
  </object>
  <object>
    <name>person</name>
    <bndbox>
      <xmin>68.97</xmin>
      <ymin>54.48</ymin>
      <xmax>415.16999999999996</xmax>
      <ymax>632.41</ymax>
    </bndbox>
  </object>
  <object>
    <name>person</name>
    <bndbox>
      <xmin>354.44</xmin>
      <ymin>66.18</ymin>
      <xmax>558.21</xmax>
      <ymax>442.14</ymax>
    </bndbox>
  </object>
  <object>
    <name>person</name>
    <bndbox>
      <xmin>0.0</xmin>
      <ymin>191.54</ymin>
      <xmax>47.12</xmax>
      <ymax>307.22</ymax>
    </bndbox>
  </object>
  <object>
    <name>cell phone</name>
    <bndbox>
      <xmin>361.33</xmin>
      <ymin>269.06</ymin>
      <xmax>399.36</xmax>
      <ymax>332.78</ymax>
    </bndbox>
  </object>
  <object>
    <name>backpack</name>
    <bndbox>
      <xmin>455.93</xmin>
      <ymin>108.85</ymin>
      <xmax>550.06</xmax>
      <ymax>220.91</ymax>
    </bndbox>
  </object>
  <object>
    <name>bicycle</name>
    <bndbox>
      <xmin>0.0</xmin>
      <ymin>290.38</ymin>
      <xmax>24.09</xmax>
      <ymax>508.74</ymax>
    </bndbox>
  </object>
  <object>
    <name>person</name>
    <bndbox>
      <xmin>170.68</xmin>
      <ymin>139.87</ymin>
      <xmax>213.29000000000002</xmax>
      <ymax>193.47</ymax>
    </bndbox>
  </object>
</annotation>
