<annotation>
  <folder>/home/nng/util/CocoToPascal/images</folder>
  <filename>000000173204.jpg</filename>
  <source>
    <database>MS COCO 2017</database>
    <annotation>MS COCO 2017</annotation>
    <image>Flickr</image>
  </source>
  <size>
    <width>640</width>
    <height>479</height>
    <depth>3</depth>
  </size>
  <segmented>0</segmented>
  <object>
    <name>person</name>
    <bndbox>
      <xmin>124.86</xmin>
      <ymin>151.59</ymin>
      <xmax>287.4</xmax>
      <ymax>418.53999999999996</ymax>
    </bndbox>
  </object>
  <object>
    <name>person</name>
    <bndbox>
      <xmin>366.94</xmin>
      <ymin>110.45</ymin>
      <xmax>506.69</xmax>
      <ymax>431.62</ymax>
    </bndbox>
  </object>
  <object>
    <name>person</name>
    <bndbox>
      <xmin>601.71</xmin>
      <ymin>215.28</ymin>
      <xmax>627.5400000000001</xmax>
      <ymax>301.39</ymax>
    </bndbox>
  </object>
  <object>
    <name>person</name>
    <bndbox>
      <xmin>324.65</xmin>
      <ymin>243.21</ymin>
      <xmax>350.97999999999996</xmax>
      <ymax>302.07</ymax>
    </bndbox>
  </object>
  <object>
    <name>person</name>
    <bndbox>
      <xmin>474.72</xmin>
      <ymin>257.21</ymin>
      <xmax>537.19</xmax>
      <ymax>414.51</ymax>
    </bndbox>
  </object>
  <object>
    <name>person</name>
    <bndbox>
      <xmin>487.78</xmin>
      <ymin>220.19</ymin>
      <xmax>497.91999999999996</xmax>
      <ymax>232.41</ymax>
    </bndbox>
  </object>
  <object>
    <name>person</name>
    <bndbox>
      <xmin>562.07</xmin>
      <ymin>214.39</ymin>
      <xmax>580.62</xmax>
      <ymax>278.69</ymax>
    </bndbox>
  </object>
  <object>
    <name>person</name>
    <bndbox>
      <xmin>279.87</xmin>
      <ymin>281.69</ymin>
      <xmax>304.62</xmax>
      <ymax>315.06</ymax>
    </bndbox>
  </object>
  <object>
    <name>skis</name>
    <bndbox>
      <xmin>349.03</xmin>
      <ymin>418.34</ymin>
      <xmax>594.47</xmax>
      <ymax>444.92999999999995</ymax>
    </bndbox>
  </object>
  <object>
    <name>person</name>
    <bndbox>
      <xmin>521.35</xmin>
      <ymin>228.0</ymin>
      <xmax>559.77</xmax>
      <ymax>303.43</ymax>
    </bndbox>
  </object>
  <object>
    <name>skis</name>
    <bndbox>
      <xmin>239.85</xmin>
      <ymin>399.48</ymin>
      <xmax>314.99</xmax>
      <ymax>411.48</ymax>
    </bndbox>
  </object>
  <object>
    <name>person</name>
    <bndbox>
      <xmin>488.11</xmin>
      <ymin>227.6</ymin>
      <xmax>513.53</xmax>
      <ymax>285.6</ymax>
    </bndbox>
  </object>
  <object>
    <name>person</name>
    <bndbox>
      <xmin>477.03</xmin>
      <ymin>222.88</ymin>
      <xmax>492.59999999999997</xmax>
      <ymax>262.55</ymax>
    </bndbox>
  </object>
  <object>
    <name>person</name>
    <bndbox>
      <xmin>295.94</xmin>
      <ymin>308.69</ymin>
      <xmax>313.48</xmax>
      <ymax>345.22</ymax>
    </bndbox>
  </object>
  <object>
    <name>person</name>
    <bndbox>
      <xmin>126.16</xmin>
      <ymin>306.56</ymin>
      <xmax>156.14</xmax>
      <ymax>343.66</ymax>
    </bndbox>
  </object>
  <object>
    <name>skis</name>
    <bndbox>
      <xmin>153.73</xmin>
      <ymin>409.69</ymin>
      <xmax>249.18</xmax>
      <ymax>421.56</ymax>
    </bndbox>
  </object>
  <object>
    <name>person</name>
    <bndbox>
      <xmin>0</xmin>
      <ymin>202</ymin>
      <xmax>639</xmax>
      <ymax>418</ymax>
    </bndbox>
  </object>
</annotation>
