<annotation>
  <folder>/home/nng/util/CocoToPascal/images</folder>
  <filename>000000549373.jpg</filename>
  <source>
    <database>MS COCO 2017</database>
    <annotation>MS COCO 2017</annotation>
    <image>Flickr</image>
  </source>
  <size>
    <width>375</width>
    <height>500</height>
    <depth>3</depth>
  </size>
  <segmented>0</segmented>
  <object>
    <name>fire hydrant</name>
    <bndbox>
      <xmin>239.08</xmin>
      <ymin>147.0</ymin>
      <xmax>366.9</xmax>
      <ymax>440.29</ymax>
    </bndbox>
  </object>
  <object>
    <name>potted plant</name>
    <bndbox>
      <xmin>59.55</xmin>
      <ymin>0.0</ymin>
      <xmax>171.91</xmax>
      <ymax>162.92</ymax>
    </bndbox>
  </object>
</annotation>
