<annotation>
  <folder>/home/nng/util/CocoToPascal/images</folder>
  <filename>000000505188.jpg</filename>
  <source>
    <database>MS COCO 2017</database>
    <annotation>MS COCO 2017</annotation>
    <image>Flickr</image>
  </source>
  <size>
    <width>640</width>
    <height>478</height>
    <depth>3</depth>
  </size>
  <segmented>0</segmented>
  <object>
    <name>remote</name>
    <bndbox>
      <xmin>282.85</xmin>
      <ymin>408.72</ymin>
      <xmax>352.07000000000005</xmax>
      <ymax>443.0</ymax>
    </bndbox>
  </object>
  <object>
    <name>remote</name>
    <bndbox>
      <xmin>121.37</xmin>
      <ymin>408.96</ymin>
      <xmax>189.88</xmax>
      <ymax>450.39</ymax>
    </bndbox>
  </object>
  <object>
    <name>cup</name>
    <bndbox>
      <xmin>234.88</xmin>
      <ymin>365.55</ymin>
      <xmax>281.36</xmax>
      <ymax>466.55</ymax>
    </bndbox>
  </object>
  <object>
    <name>cup</name>
    <bndbox>
      <xmin>59.2</xmin>
      <ymin>387.77</ymin>
      <xmax>121.57</xmax>
      <ymax>452.26</ymax>
    </bndbox>
  </object>
  <object>
    <name>cup</name>
    <bndbox>
      <xmin>290.43</xmin>
      <ymin>369.31</ymin>
      <xmax>328.03000000000003</xmax>
      <ymax>410.8</ymax>
    </bndbox>
  </object>
  <object>
    <name>cell phone</name>
    <bndbox>
      <xmin>196.8</xmin>
      <ymin>429.28</ymin>
      <xmax>239.82000000000002</xmax>
      <ymax>454.52</ymax>
    </bndbox>
  </object>
  <object>
    <name>book</name>
    <bndbox>
      <xmin>60.51</xmin>
      <ymin>257.65</ymin>
      <xmax>113.37</xmax>
      <ymax>281.15</ymax>
    </bndbox>
  </object>
  <object>
    <name>bottle</name>
    <bndbox>
      <xmin>20.74</xmin>
      <ymin>223.13</ymin>
      <xmax>42.01</xmax>
      <ymax>276.14</ymax>
    </bndbox>
  </object>
  <object>
    <name>cup</name>
    <bndbox>
      <xmin>1.24</xmin>
      <ymin>386.12</ymin>
      <xmax>60.84</xmax>
      <ymax>458.14</ymax>
    </bndbox>
  </object>
  <object>
    <name>person</name>
    <bndbox>
      <xmin>611.03</xmin>
      <ymin>391.26</ymin>
      <xmax>640.0</xmax>
      <ymax>468.24</ymax>
    </bndbox>
  </object>
</annotation>
