<annotation>
  <folder>/home/nng/util/CocoToPascal/images</folder>
  <filename>000000074206.jpg</filename>
  <source>
    <database>MS COCO 2017</database>
    <annotation>MS COCO 2017</annotation>
    <image>Flickr</image>
  </source>
  <size>
    <width>500</width>
    <height>375</height>
    <depth>3</depth>
  </size>
  <segmented>0</segmented>
  <object>
    <name>laptop</name>
    <bndbox>
      <xmin>179.49</xmin>
      <ymin>106.18</ymin>
      <xmax>405.34000000000003</xmax>
      <ymax>340.45000000000005</ymax>
    </bndbox>
  </object>
  <object>
    <name>mouse</name>
    <bndbox>
      <xmin>364.68</xmin>
      <ymin>307.51</ymin>
      <xmax>398.43</xmax>
      <ymax>350.06</ymax>
    </bndbox>
  </object>
  <object>
    <name>book</name>
    <bndbox>
      <xmin>448.41</xmin>
      <ymin>352.83</ymin>
      <xmax>499.79</xmax>
      <ymax>375.0</ymax>
    </bndbox>
  </object>
  <object>
    <name>chair</name>
    <bndbox>
      <xmin>2.53</xmin>
      <ymin>303.37</ymin>
      <xmax>109.55</xmax>
      <ymax>375.0</ymax>
    </bndbox>
  </object>
  <object>
    <name>book</name>
    <bndbox>
      <xmin>438.02</xmin>
      <ymin>304.88</ymin>
      <xmax>500.0</xmax>
      <ymax>352.45</ymax>
    </bndbox>
  </object>
  <object>
    <name>book</name>
    <bndbox>
      <xmin>311.58</xmin>
      <ymin>287.35</ymin>
      <xmax>443.45</xmax>
      <ymax>375.0</ymax>
    </bndbox>
  </object>
  <object>
    <name>tv</name>
    <bndbox>
      <xmin>13.45</xmin>
      <ymin>92.34</ymin>
      <xmax>202.42</xmax>
      <ymax>266.03</ymax>
    </bndbox>
  </object>
</annotation>
