<annotation>
  <folder>/home/nng/util/CocoToPascal/images</folder>
  <filename>000000134902.jpg</filename>
  <source>
    <database>MS COCO 2017</database>
    <annotation>MS COCO 2017</annotation>
    <image>Flickr</image>
  </source>
  <size>
    <width>620</width>
    <height>413</height>
    <depth>3</depth>
  </size>
  <segmented>0</segmented>
  <object>
    <name>toilet</name>
    <bndbox>
      <xmin>271.0</xmin>
      <ymin>209.75</ymin>
      <xmax>340.61</xmax>
      <ymax>350.82</ymax>
    </bndbox>
  </object>
  <object>
    <name>sink</name>
    <bndbox>
      <xmin>419.2</xmin>
      <ymin>241.61</ymin>
      <xmax>587.18</xmax>
      <ymax>342.65000000000003</ymax>
    </bndbox>
  </object>
</annotation>
