<annotation>
  <folder>/home/nng/util/CocoToPascal/images</folder>
  <filename>000000415322.jpg</filename>
  <source>
    <database>MS COCO 2017</database>
    <annotation>MS COCO 2017</annotation>
    <image>Flickr</image>
  </source>
  <size>
    <width>640</width>
    <height>480</height>
    <depth>3</depth>
  </size>
  <segmented>0</segmented>
  <object>
    <name>donut</name>
    <bndbox>
      <xmin>189.08</xmin>
      <ymin>129.88</ymin>
      <xmax>256.43</xmax>
      <ymax>191.62</ymax>
    </bndbox>
  </object>
  <object>
    <name>donut</name>
    <bndbox>
      <xmin>486.2</xmin>
      <ymin>203.11</ymin>
      <xmax>574.15</xmax>
      <ymax>279.90000000000003</ymax>
    </bndbox>
  </object>
  <object>
    <name>donut</name>
    <bndbox>
      <xmin>251.22</xmin>
      <ymin>169.55</ymin>
      <xmax>309.12</xmax>
      <ymax>232.17000000000002</ymax>
    </bndbox>
  </object>
  <object>
    <name>donut</name>
    <bndbox>
      <xmin>391.8</xmin>
      <ymin>252.86</ymin>
      <xmax>475.78000000000003</xmax>
      <ymax>304.98</ymax>
    </bndbox>
  </object>
  <object>
    <name>donut</name>
    <bndbox>
      <xmin>360.86</xmin>
      <ymin>242.53</ymin>
      <xmax>426.41</xmax>
      <ymax>281.96</ymax>
    </bndbox>
  </object>
  <object>
    <name>donut</name>
    <bndbox>
      <xmin>214.17</xmin>
      <ymin>209.42</ymin>
      <xmax>274.74</xmax>
      <ymax>240.97</ymax>
    </bndbox>
  </object>
  <object>
    <name>donut</name>
    <bndbox>
      <xmin>427.64</xmin>
      <ymin>206.96</ymin>
      <xmax>516.16</xmax>
      <ymax>266.81</ymax>
    </bndbox>
  </object>
  <object>
    <name>donut</name>
    <bndbox>
      <xmin>97.21</xmin>
      <ymin>122.7</ymin>
      <xmax>155.55</xmax>
      <ymax>171.01</ymax>
    </bndbox>
  </object>
  <object>
    <name>donut</name>
    <bndbox>
      <xmin>132.8</xmin>
      <ymin>167.36</ymin>
      <xmax>204.58</xmax>
      <ymax>218.07000000000002</ymax>
    </bndbox>
  </object>
  <object>
    <name>donut</name>
    <bndbox>
      <xmin>298.88</xmin>
      <ymin>217.53</ymin>
      <xmax>367.5</xmax>
      <ymax>262.45</ymax>
    </bndbox>
  </object>
</annotation>
