<annotation>
  <folder>/home/nng/util/CocoToPascal/images</folder>
  <filename>000000091275.jpg</filename>
  <source>
    <database>MS COCO 2017</database>
    <annotation>MS COCO 2017</annotation>
    <image>Flickr</image>
  </source>
  <size>
    <width>612</width>
    <height>612</height>
    <depth>3</depth>
  </size>
  <segmented>0</segmented>
  <object>
    <name>animal</name>
    <bndbox>
      <xmin>210.18</xmin>
      <ymin>83.7</ymin>
      <xmax>372.15</xmax>
      <ymax>553.52</ymax>
    </bndbox>
  </object>
  <object>
    <name>frisbee</name>
    <bndbox>
      <xmin>215.92</xmin>
      <ymin>284.68</ymin>
      <xmax>389.2</xmax>
      <ymax>470.35</ymax>
    </bndbox>
  </object>
</annotation>
