<annotation>
  <folder>/home/nng/util/CocoToPascal/images</folder>
  <filename>000000118051.jpg</filename>
  <source>
    <database>MS COCO 2017</database>
    <annotation>MS COCO 2017</annotation>
    <image>Flickr</image>
  </source>
  <size>
    <width>500</width>
    <height>375</height>
    <depth>3</depth>
  </size>
  <segmented>0</segmented>
  <object>
    <name>cell phone</name>
    <bndbox>
      <xmin>111.37</xmin>
      <ymin>284.76</ymin>
      <xmax>150.28</xmax>
      <ymax>302.62</ymax>
    </bndbox>
  </object>
  <object>
    <name>laptop</name>
    <bndbox>
      <xmin>179.74</xmin>
      <ymin>137.95</ymin>
      <xmax>279.13</xmax>
      <ymax>225.52999999999997</ymax>
    </bndbox>
  </object>
  <object>
    <name>mouse</name>
    <bndbox>
      <xmin>326.85</xmin>
      <ymin>219.77</ymin>
      <xmax>355.75</xmax>
      <ymax>233.66000000000003</ymax>
    </bndbox>
  </object>
  <object>
    <name>keyboard</name>
    <bndbox>
      <xmin>224.34</xmin>
      <ymin>222.36</ymin>
      <xmax>329.65</xmax>
      <ymax>258.48</ymax>
    </bndbox>
  </object>
  <object>
    <name>book</name>
    <bndbox>
      <xmin>363.63</xmin>
      <ymin>241.4</ymin>
      <xmax>428.19</xmax>
      <ymax>275.84000000000003</ymax>
    </bndbox>
  </object>
  <object>
    <name>scissors</name>
    <bndbox>
      <xmin>120.69</xmin>
      <ymin>197.04</ymin>
      <xmax>137.28</xmax>
      <ymax>221.54999999999998</ymax>
    </bndbox>
  </object>
  <object>
    <name>clock</name>
    <bndbox>
      <xmin>480.57</xmin>
      <ymin>207.38</ymin>
      <xmax>500.0</xmax>
      <ymax>240.7</ymax>
    </bndbox>
  </object>
  <object>
    <name>tv</name>
    <bndbox>
      <xmin>236.77</xmin>
      <ymin>117.89</ymin>
      <xmax>313.06</xmax>
      <ymax>183.23000000000002</ymax>
    </bndbox>
  </object>
  <object>
    <name>keyboard</name>
    <bndbox>
      <xmin>195.82</xmin>
      <ymin>193.01</ymin>
      <xmax>260.52</xmax>
      <ymax>212.88</ymax>
    </bndbox>
  </object>
  <object>
    <name>book</name>
    <bndbox>
      <xmin>0.0</xmin>
      <ymin>261.91</ymin>
      <xmax>36.86</xmax>
      <ymax>309.70000000000005</ymax>
    </bndbox>
  </object>
</annotation>
