<annotation>
  <folder>/home/nng/util/CocoToPascal/images</folder>
  <filename>000000157279.jpg</filename>
  <source>
    <database>MS COCO 2017</database>
    <annotation>MS COCO 2017</annotation>
    <image>Flickr</image>
  </source>
  <size>
    <width>480</width>
    <height>640</height>
    <depth>3</depth>
  </size>
  <segmented>0</segmented>
  <object>
    <name>parking meter</name>
    <bndbox>
      <xmin>216.92</xmin>
      <ymin>45.26</ymin>
      <xmax>299.95</xmax>
      <ymax>214.04</ymax>
    </bndbox>
  </object>
  <object>
    <name>potted plant</name>
    <bndbox>
      <xmin>58.05</xmin>
      <ymin>104.36</ymin>
      <xmax>194.5</xmax>
      <ymax>234.20999999999998</ymax>
    </bndbox>
  </object>
  <object>
    <name>potted plant</name>
    <bndbox>
      <xmin>0.0</xmin>
      <ymin>123.01</ymin>
      <xmax>104.73</xmax>
      <ymax>226.07999999999998</ymax>
    </bndbox>
  </object>
  <object>
    <name>potted plant</name>
    <bndbox>
      <xmin>284.84</xmin>
      <ymin>103.07</ymin>
      <xmax>480.0</xmax>
      <ymax>251.91</ymax>
    </bndbox>
  </object>
</annotation>
