<annotation>
  <folder>/home/nng/util/CocoToPascal/images</folder>
  <filename>000000537532.jpg</filename>
  <source>
    <database>MS COCO 2017</database>
    <annotation>MS COCO 2017</annotation>
    <image>Flickr</image>
  </source>
  <size>
    <width>640</width>
    <height>480</height>
    <depth>3</depth>
  </size>
  <segmented>0</segmented>
  <object>
    <name>person</name>
    <bndbox>
      <xmin>1.08</xmin>
      <ymin>0.0</ymin>
      <xmax>406.65</xmax>
      <ymax>106.79</ymax>
    </bndbox>
  </object>
  <object>
    <name>spoon</name>
    <bndbox>
      <xmin>0.0</xmin>
      <ymin>101.23</ymin>
      <xmax>142.26</xmax>
      <ymax>165.97</ymax>
    </bndbox>
  </object>
  <object>
    <name>bowl</name>
    <bndbox>
      <xmin>0.0</xmin>
      <ymin>93.91</ymin>
      <xmax>258.88</xmax>
      <ymax>231.98</ymax>
    </bndbox>
  </object>
  <object>
    <name>bowl</name>
    <bndbox>
      <xmin>267.38</xmin>
      <ymin>94.6</ymin>
      <xmax>503.62</xmax>
      <ymax>179.43</ymax>
    </bndbox>
  </object>
  <object>
    <name>broccoli</name>
    <bndbox>
      <xmin>282.35</xmin>
      <ymin>154.38</ymin>
      <xmax>591.81</xmax>
      <ymax>355.41999999999996</ymax>
    </bndbox>
  </object>
  <object>
    <name>broccoli</name>
    <bndbox>
      <xmin>93.37</xmin>
      <ymin>296.27</ymin>
      <xmax>208.63</xmax>
      <ymax>466.96999999999997</ymax>
    </bndbox>
  </object>
  <object>
    <name>broccoli</name>
    <bndbox>
      <xmin>101.91</xmin>
      <ymin>238.58</ymin>
      <xmax>279.90999999999997</xmax>
      <ymax>393.59000000000003</ymax>
    </bndbox>
  </object>
  <object>
    <name>broccoli</name>
    <bndbox>
      <xmin>353.51</xmin>
      <ymin>303.81</ymin>
      <xmax>472.09</xmax>
      <ymax>455.15</ymax>
    </bndbox>
  </object>
  <object>
    <name>broccoli</name>
    <bndbox>
      <xmin>445.01</xmin>
      <ymin>279.5</ymin>
      <xmax>512.41</xmax>
      <ymax>333.78</ymax>
    </bndbox>
  </object>
  <object>
    <name>spoon</name>
    <bndbox>
      <xmin>455.19</xmin>
      <ymin>168.27</ymin>
      <xmax>639.64</xmax>
      <ymax>295.55</ymax>
    </bndbox>
  </object>
  <object>
    <name>bowl</name>
    <bndbox>
      <xmin>26.97</xmin>
      <ymin>173.66</ymin>
      <xmax>622.38</xmax>
      <ymax>480.0</ymax>
    </bndbox>
  </object>
  <object>
    <name>bowl</name>
    <bndbox>
      <xmin>3.24</xmin>
      <ymin>165.03</ymin>
      <xmax>42.07</xmax>
      <ymax>357.03</ymax>
    </bndbox>
  </object>
  <object>
    <name>broccoli</name>
    <bndbox>
      <xmin>272.9</xmin>
      <ymin>283.69</ymin>
      <xmax>363.51</xmax>
      <ymax>358.11</ymax>
    </bndbox>
  </object>
  <object>
    <name>broccoli</name>
    <bndbox>
      <xmin>483.2</xmin>
      <ymin>338.85</ymin>
      <xmax>567.5</xmax>
      <ymax>410.0</ymax>
    </bndbox>
  </object>
  <object>
    <name>broccoli</name>
    <bndbox>
      <xmin>283.69</xmin>
      <ymin>366.56</ymin>
      <xmax>341.93</xmax>
      <ymax>429.12</ymax>
    </bndbox>
  </object>
  <object>
    <name>person</name>
    <bndbox>
      <xmin>442.25</xmin>
      <ymin>1.08</ymin>
      <xmax>640.0</xmax>
      <ymax>143.46</ymax>
    </bndbox>
  </object>
  <object>
    <name>broccoli</name>
    <bndbox>
      <xmin>97.02</xmin>
      <ymin>347.9</ymin>
      <xmax>156.74</xmax>
      <ymax>408.9</ymax>
    </bndbox>
  </object>
  <object>
    <name>broccoli</name>
    <bndbox>
      <xmin>190.59</xmin>
      <ymin>401.07</ymin>
      <xmax>294.15999999999997</xmax>
      <ymax>480.0</ymax>
    </bndbox>
  </object>
</annotation>
