<annotation>
  <folder>/home/nng/util/CocoToPascal/images</folder>
  <filename>000000450160.jpg</filename>
  <source>
    <database>MS COCO 2017</database>
    <annotation>MS COCO 2017</annotation>
    <image>Flickr</image>
  </source>
  <size>
    <width>640</width>
    <height>480</height>
    <depth>3</depth>
  </size>
  <segmented>0</segmented>
  <object>
    <name>animal</name>
    <bndbox>
      <xmin>137.42</xmin>
      <ymin>184.84</ymin>
      <xmax>269.03</xmax>
      <ymax>283.55</ymax>
    </bndbox>
  </object>
  <object>
    <name>bench</name>
    <bndbox>
      <xmin>242.36</xmin>
      <ymin>135.06</ymin>
      <xmax>497.4</xmax>
      <ymax>268.7</ymax>
    </bndbox>
  </object>
  <object>
    <name>backpack</name>
    <bndbox>
      <xmin>262.58</xmin>
      <ymin>138.84</ymin>
      <xmax>312.7</xmax>
      <ymax>190.68</ymax>
    </bndbox>
  </object>
</annotation>
