<annotation>
  <folder>/home/nng/util/CocoToPascal/images</folder>
  <filename>000000460885.jpg</filename>
  <source>
    <database>MS COCO 2017</database>
    <annotation>MS COCO 2017</annotation>
    <image>Flickr</image>
  </source>
  <size>
    <width>478</width>
    <height>640</height>
    <depth>3</depth>
  </size>
  <segmented>0</segmented>
  <object>
    <name>chair</name>
    <bndbox>
      <xmin>0.0</xmin>
      <ymin>409.62</ymin>
      <xmax>286.35</xmax>
      <ymax>632.98</ymax>
    </bndbox>
  </object>
  <object>
    <name>chair</name>
    <bndbox>
      <xmin>317.13</xmin>
      <ymin>395.98</ymin>
      <xmax>478.0</xmax>
      <ymax>627.01</ymax>
    </bndbox>
  </object>
  <object>
    <name>person</name>
    <bndbox>
      <xmin>42.47</xmin>
      <ymin>176.79</ymin>
      <xmax>235.34</xmax>
      <ymax>412.13</ymax>
    </bndbox>
  </object>
  <object>
    <name>person</name>
    <bndbox>
      <xmin>297.46</xmin>
      <ymin>171.75</ymin>
      <xmax>450.49</xmax>
      <ymax>431.37</ymax>
    </bndbox>
  </object>
  <object>
    <name>laptop</name>
    <bndbox>
      <xmin>46.7</xmin>
      <ymin>199.19</ymin>
      <xmax>169.78</xmax>
      <ymax>323.22</ymax>
    </bndbox>
  </object>
  <object>
    <name>laptop</name>
    <bndbox>
      <xmin>242.86</xmin>
      <ymin>184.29</ymin>
      <xmax>312.76</xmax>
      <ymax>297.58</ymax>
    </bndbox>
  </object>
  <object>
    <name>mouse</name>
    <bndbox>
      <xmin>407.96</xmin>
      <ymin>263.04</ymin>
      <xmax>424.75</xmax>
      <ymax>275.95000000000005</ymax>
    </bndbox>
  </object>
</annotation>
