<annotation>
  <folder>/home/nng/util/CocoToPascal/images</folder>
  <filename>000000372558.jpg</filename>
  <source>
    <database>MS COCO 2017</database>
    <annotation>MS COCO 2017</annotation>
    <image>Flickr</image>
  </source>
  <size>
    <width>640</width>
    <height>401</height>
    <depth>3</depth>
  </size>
  <segmented>0</segmented>
  <object>
    <name>boat</name>
    <bndbox>
      <xmin>186.53</xmin>
      <ymin>47.76</ymin>
      <xmax>608.26</xmax>
      <ymax>364.96</ymax>
    </bndbox>
  </object>
  <object>
    <name>boat</name>
    <bndbox>
      <xmin>57.28</xmin>
      <ymin>196.6</ymin>
      <xmax>212.65</xmax>
      <ymax>351.7</ymax>
    </bndbox>
  </object>
  <object>
    <name>boat</name>
    <bndbox>
      <xmin>287.54</xmin>
      <ymin>287.3</ymin>
      <xmax>329.07000000000005</xmax>
      <ymax>320.65000000000003</ymax>
    </bndbox>
  </object>
</annotation>
