<annotation>
  <folder>/home/nng/util/CocoToPascal/images</folder>
  <filename>000000068409.jpg</filename>
  <source>
    <database>MS COCO 2017</database>
    <annotation>MS COCO 2017</annotation>
    <image>Flickr</image>
  </source>
  <size>
    <width>640</width>
    <height>263</height>
    <depth>3</depth>
  </size>
  <segmented>0</segmented>
  <object>
    <name>accessory</name>
    <bndbox>
      <xmin>416.61</xmin>
      <ymin>81.02</ymin>
      <xmax>424.53000000000003</xmax>
      <ymax>102.82</ymax>
    </bndbox>
  </object>
  <object>
    <name>person</name>
    <bndbox>
      <xmin>475.25</xmin>
      <ymin>19.27</ymin>
      <xmax>636.97</xmax>
      <ymax>258.79</ymax>
    </bndbox>
  </object>
  <object>
    <name>person</name>
    <bndbox>
      <xmin>504.34</xmin>
      <ymin>2.35</ymin>
      <xmax>639.0</xmax>
      <ymax>96.41999999999999</ymax>
    </bndbox>
  </object>
  <object>
    <name>person</name>
    <bndbox>
      <xmin>201.93</xmin>
      <ymin>17.24</ymin>
      <xmax>368.39</xmax>
      <ymax>247.29000000000002</ymax>
    </bndbox>
  </object>
  <object>
    <name>person</name>
    <bndbox>
      <xmin>347.92</xmin>
      <ymin>6.32</ymin>
      <xmax>485.4</xmax>
      <ymax>259.04</ymax>
    </bndbox>
  </object>
  <object>
    <name>person</name>
    <bndbox>
      <xmin>409.63</xmin>
      <ymin>1.34</ymin>
      <xmax>517.9</xmax>
      <ymax>151.56</ymax>
    </bndbox>
  </object>
  <object>
    <name>person</name>
    <bndbox>
      <xmin>254.52</xmin>
      <ymin>1.8900000000000001</ymin>
      <xmax>410.09000000000003</xmax>
      <ymax>93.48</ymax>
    </bndbox>
  </object>
  <object>
    <name>person</name>
    <bndbox>
      <xmin>89.37</xmin>
      <ymin>1.15</ymin>
      <xmax>183.04000000000002</xmax>
      <ymax>82.45</ymax>
    </bndbox>
  </object>
  <object>
    <name>person</name>
    <bndbox>
      <xmin>111.01</xmin>
      <ymin>18.44</ymin>
      <xmax>264.0</xmax>
      <ymax>251.65</ymax>
    </bndbox>
  </object>
  <object>
    <name>person</name>
    <bndbox>
      <xmin>4.55</xmin>
      <ymin>6.63</ymin>
      <xmax>150.64000000000001</xmax>
      <ymax>257.56</ymax>
    </bndbox>
  </object>
  <object>
    <name>accessory</name>
    <bndbox>
      <xmin>292.31</xmin>
      <ymin>91.41</ymin>
      <xmax>305.66</xmax>
      <ymax>120.89</ymax>
    </bndbox>
  </object>
  <object>
    <name>accessory</name>
    <bndbox>
      <xmin>193.68</xmin>
      <ymin>82.79</ymin>
      <xmax>207.3</xmax>
      <ymax>118.66</ymax>
    </bndbox>
  </object>
  <object>
    <name>accessory</name>
    <bndbox>
      <xmin>81.17</xmin>
      <ymin>78.34</ymin>
      <xmax>93.78</xmax>
      <ymax>105.55000000000001</ymax>
    </bndbox>
  </object>
  <object>
    <name>accessory</name>
    <bndbox>
      <xmin>562.48</xmin>
      <ymin>90.57</ymin>
      <xmax>570.26</xmax>
      <ymax>109.97</ymax>
    </bndbox>
  </object>
  <object>
    <name>person</name>
    <bndbox>
      <xmin>210.78</xmin>
      <ymin>3.13</ymin>
      <xmax>281.19</xmax>
      <ymax>79.69</ymax>
    </bndbox>
  </object>
  <object>
    <name>accessory</name>
    <bndbox>
      <xmin>455.0</xmin>
      <ymin>1.07</ymin>
      <xmax>464.86</xmax>
      <ymax>15.3</ymax>
    </bndbox>
  </object>
</annotation>
